torch_tensorrt/dynamo/__init__.py
torch_tensorrt/dynamo/fx_ts_compat/__init__.py
torch_tensorrt/dynamo/fx_ts_compat/fx2trt.py
torch_tensorrt/dynamo/fx_ts_compat/input_tensor_spec.py
torch_tensorrt/dynamo/fx_ts_compat/lower.py
torch_tensorrt/dynamo/fx_ts_compat/lower_setting.py
torch_tensorrt/dynamo/fx_ts_compat/passes/__init__.py
torch_tensorrt/dynamo/fx_ts_compat/passes/lower_pass_manager_builder.py
torch_tensorrt/dynamo/fx_ts_compat/passes/pass_utils.py
torch_tensorrt/dynamo/fx_ts_compat/tools/__init__.py
torch_tensorrt/dynamo/fx_ts_compat/tools/common_fx2trt.py
torch_tensorrt/dynamo/fx_ts_compat/tools/trt_minimizer.py
torch_tensorrt/fx/__init__.py
torch_tensorrt/fx/converter_registry.py
torch_tensorrt/fx/diagnostics.py
torch_tensorrt/fx/fx2trt.py
torch_tensorrt/fx/input_tensor_spec.py
torch_tensorrt/fx/lower.py
torch_tensorrt/fx/lower_setting.py
torch_tensorrt/fx/observer.py
torch_tensorrt/fx/trt_module.py
torch_tensorrt/fx/types.py
torch_tensorrt/fx/utils.py
torch_tensorrt/fx/converters/__init__.py
torch_tensorrt/fx/converters/acc_ops_converters.py
torch_tensorrt/fx/converters/adaptive_avgpool.py
torch_tensorrt/fx/converters/add.py
torch_tensorrt/fx/converters/aten_ops_converters.py
torch_tensorrt/fx/converters/batchnorm.py
torch_tensorrt/fx/converters/converter_utils.py
torch_tensorrt/fx/converters/convolution.py
torch_tensorrt/fx/converters/linear.py
torch_tensorrt/fx/converters/maxpool.py
torch_tensorrt/fx/converters/mul.py
torch_tensorrt/fx/converters/nn_ops_converters.py
torch_tensorrt/fx/converters/quantization.py
torch_tensorrt/fx/converters/transformation.py
torch_tensorrt/fx/converters/impl/__init__.py
torch_tensorrt/fx/converters/impl/activation.py
torch_tensorrt/fx/passes/__init__.py
torch_tensorrt/fx/passes/graph_opts.py
torch_tensorrt/fx/passes/lower_basic_pass.py
torch_tensorrt/fx/passes/lower_basic_pass_aten.py
torch_tensorrt/fx/passes/lower_pass_manager_builder.py
torch_tensorrt/fx/passes/pass_utils.py
torch_tensorrt_fx_only-1.4.0.post1.dist-info/LICENSE
torch_tensorrt_fx_only-1.4.0.post1.dist-info/METADATA
torch_tensorrt_fx_only-1.4.0.post1.dist-info/WHEEL
torch_tensorrt_fx_only-1.4.0.post1.dist-info/top_level.txt
torch_tensorrt_fx_only-1.4.0.post1.dist-info/RECORD
