Metadata-Version: 2.1
Name: torch-tensorrt-fx-only
Version: 1.4.0.post1
Summary: Unofficial Torch-TensorRT Python package built with FX path only
Home-page: https://nvidia.github.io/torch-tensorrt
License: BSD
Classifier: Development Status :: 5 - Production/Stable
Classifier: Environment :: GPU :: NVIDIA CUDA
Classifier: License :: OSI Approved :: BSD License
Classifier: Intended Audience :: Developers
Classifier: Intended Audience :: Science/Research
Classifier: Operating System :: POSIX :: Linux
Classifier: Programming Language :: C++
Classifier: Programming Language :: Python
Classifier: Programming Language :: Python :: Implementation :: CPython
Classifier: Topic :: Scientific/Engineering
Classifier: Topic :: Scientific/Engineering :: Artificial Intelligence
Classifier: Topic :: Software Development
Classifier: Topic :: Software Development :: Libraries
Requires-Python: >=3.8
License-File: LICENSE
Requires-Dist: torch (<2.2,>=2.0.1)
